pylbc/__init__.py
pylbc/pylbc.py
pylbc-1.0.3.dist-info/DESCRIPTION.rst
pylbc-1.0.3.dist-info/METADATA
pylbc-1.0.3.dist-info/RECORD
pylbc-1.0.3.dist-info/WHEEL
pylbc-1.0.3.dist-info/metadata.json
pylbc-1.0.3.dist-info/top_level.txt
